Automation3270Library/__init__.py
Automation3270Library-0.1.0.dist-info/LICENSE
Automation3270Library-0.1.0.dist-info/METADATA
Automation3270Library-0.1.0.dist-info/WHEEL
Automation3270Library-0.1.0.dist-info/top_level.txt
Automation3270Library-0.1.0.dist-info/RECORD
